MANIFEST.in
README.txt
setup.py
docs/HISTORY.txt
docs/INSTALL.txt
docs/LICENSE.GPL
docs/LICENSE.txt
wildcard/__init__.py
wildcard.foldercontents.egg-info/PKG-INFO
wildcard.foldercontents.egg-info/SOURCES.txt
wildcard.foldercontents.egg-info/dependency_links.txt
wildcard.foldercontents.egg-info/entry_points.txt
wildcard.foldercontents.egg-info/namespace_packages.txt
wildcard.foldercontents.egg-info/not-zip-safe
wildcard.foldercontents.egg-info/requires.txt
wildcard.foldercontents.egg-info/top_level.txt
wildcard/foldercontents/__init__.py
wildcard/foldercontents/batching.pt
wildcard/foldercontents/configure.zcml
wildcard/foldercontents/factories.py
wildcard/foldercontents/folder_contents.pt
wildcard/foldercontents/i18n.sh
wildcard/foldercontents/interfaces.py
wildcard/foldercontents/jstemplates.py
wildcard/foldercontents/table.pt
wildcard/foldercontents/views.py
wildcard/foldercontents/Extensions/install.py
wildcard/foldercontents/locales/manual.pot
wildcard/foldercontents/locales/wildcard.foldercontents.pot
wildcard/foldercontents/locales/ca/LC_MESSAGES/wildcard.foldercontents.po
wildcard/foldercontents/locales/de/LC_MESSAGES/wildcard.foldercontents.po
wildcard/foldercontents/locales/es/LC_MESSAGES/wildcard.foldercontents.po
wildcard/foldercontents/locales/fr/LC_MESSAGES/wildcard.foldercontents.po
wildcard/foldercontents/locales/it/LC_MESSAGES/wildcard.foldercontents.po
wildcard/foldercontents/locales/nl/LC_MESSAGES/wildcard.foldercontents.po
wildcard/foldercontents/locales/zh_CN/LC_MESSAGES/wildcard.foldercontents.po
wildcard/foldercontents/profiles/default/browserlayer.xml
wildcard/foldercontents/profiles/default/metadata.xml
wildcard/foldercontents/profiles/uninstall/browserlayer.xml
wildcard/foldercontents/resources/integration.js
wildcard/foldercontents/resources/jquery.js
wildcard/foldercontents/resources/locale.js
wildcard/foldercontents/resources/bootstrap/bootstrap-fixed.css
wildcard/foldercontents/resources/bootstrap/bootstrap-orig.css
wildcard/foldercontents/resources/bootstrap/bootstrap.min.js
wildcard/foldercontents/resources/bootstrap/fix-bootstrap.py
wildcard/foldercontents/resources/bootstrap/glyphicons-halflings-white.png
wildcard/foldercontents/resources/bootstrap/glyphicons-halflings.png
wildcard/foldercontents/resources/img/uploadify-cancel.png
