Metadata-Version: 1.1
Name: wildcard.foldercontents
Version: 1.3.3
Summary: better folder contents implementation
Home-page: https://github.com/collective/wildcard.foldercontents
Author: Nathan Van Gheem
Author-email: vangheem@gmail.com
License: GPL
Keywords: plone folder contents drag drop upload reorder sort
Platform: UNKNOWN
Classifier: Framework :: Plone
Classifier: Programming Language :: Python
